[{"nom_ar":"مهن الـخـدمـات","nom_fr":"METIERS DES SERVICES","count":31,"places":739,"inscrits":919},{"nom_ar":"البناء و الأشغال العمومية","nom_fr":"BATIMENT - TRAVAUX PUBLICS","count":25,"places":448,"inscrits":612},{"nom_ar":"الفلاحة","nom_fr":"AGRICULTURE","count":23,"places":366,"inscrits":405},{"nom_ar":"الفندقة الإطعام و السياحة","nom_fr":"HOTELLERIE - RESTAURTION-TOURISME","count":17,"places":325,"inscrits":513},{"nom_ar":"الكهرباء - الإلكترونيك- طاقوية","nom_fr":"ELECTRICITE - ELECTRONIQUE - ENERGETIQUE","count":17,"places":362,"inscrits":402},{"nom_ar":"النسيج و الألبسة","nom_fr":"TEXTILES-HABILLEMENT-CONFECTION","count":15,"places":430,"inscrits":401},{"nom_ar":"تقنيات الادارة و التسيير","nom_fr":"TECHNIQUES ADMINISTRATIVES ET DE GESTION","count":12,"places":300,"inscrits":516},{"nom_ar":"مهن  المياه والبيئة","nom_fr":"METIERS DE L’EAU ET DE L’ENVIRONNEMENT","count":12,"places":270,"inscrits":326},{"nom_ar":"الحرف التقليدية","nom_fr":"ARTISANAT TRADITIONNEL","count":8,"places":200,"inscrits":71},{"nom_ar":"إعلام آلي _الرقمنة_الإتصالات","nom_fr":"INFORMATIQUE-NUMERIQUE-TELECOM","count":7,"places":190,"inscrits":224},{"nom_ar":"صناعة الأغذية الزراعية","nom_fr":"INDUSTRIES AGROALIMENTAIRES","count":2,"places":40,"inscrits":52},{"nom_ar":"الكيمياء الصناعية و البلاستيكية","nom_fr":"CHIMIE INDUSTRIELLE ET PLASTURIE","count":1,"places":10,"inscrits":12}]